messytables/core.py
messytables/util.py
messytables/__init__.py
messytables/types.py
messytables/commas.py
messytables/headers.py
messytables/zip.py
messytables/jts.py
messytables/dateparser.py
messytables/pdf.py
messytables/ods.py
messytables/excel.py
messytables/any.py
messytables/ilines.py
messytables/error.py
messytables/html.py
messytables-0.14.5.dist-info/namespace_packages.txt
messytables-0.14.5.dist-info/entry_points.txt
messytables-0.14.5.dist-info/WHEEL
messytables-0.14.5.dist-info/METADATA
messytables-0.14.5.dist-info/DESCRIPTION.rst
messytables-0.14.5.dist-info/metadata.json
messytables-0.14.5.dist-info/top_level.txt
messytables-0.14.5.dist-info/RECORD
