Metadata-Version: 2.0
Name: messytables
Version: 0.14.5
Summary: Parse messy tabular data in various formats
Home-page: http://okfn.org
Author: Open Knowledge Foundation
Author-email: info@okfn.org
License: MIT
Platform: UNKNOWN
Classifier: Development Status :: 4 - Beta
Classifier: Intended Audience :: Developers
Classifier: License :: OSI Approved :: MIT License
Classifier: Operating System :: OS Independent
Classifier: Programming Language :: Python
Requires-Dist: xlrd (>=0.8.0)
Requires-Dist: python-magic (==0.4.6)
Requires-Dist: chardet (==2.1.1)
Requires-Dist: python-dateutil (>=1.5.0,<2.0.0)
Requires-Dist: json-table-schema
Requires-Dist: lxml (>=3.2)
Requires-Dist: requests
Requires-Dist: html5lib
Provides-Extra: pdf
Requires-Dist: pdftables (>=0.0.4); extra == 'pdf'
